COPYING
COPYING.LESSER
README.md
__init__.py
alea.py
blea.py
clea.py
dlea.py
evidence_ctx.py
ext_decimal.py
ext_fraction.py
flea.py
flea1.py
flea2.py
flea2a.py
glea.py
ilea.py
lea.py
leaf.py
license.py
markov.py
number.py
olea.py
plea.py
prob_decimal.py
prob_fraction.py
rlea.py
setup.py
slea.py
tlea.py
toolbox.py
lea.egg-info/PKG-INFO
lea.egg-info/SOURCES.txt
lea.egg-info/dependency_links.txt
lea.egg-info/top_level.txt