Metadata-Version: 2.1
Name: lea
Version: 3.4.6
Summary: Discrete probability distributions in Python
Home-page: http://bitbucket.org/piedenis/lea
Author: Pierre Denis
Author-email: pie.denis@skynet.be
License: LGPL
Keywords: probability,discrete,distribution,probabilistic programming
Classifier: Development Status :: 5 - Production/Stable
Classifier: Programming Language :: Python :: 2.6
Classifier: Programming Language :: Python :: 2.7
Classifier: Programming Language :: Python :: 3
Classifier: Topic :: Utilities
Classifier: Topic :: Scientific/Engineering :: Artificial Intelligence
Classifier: Topic :: Scientific/Engineering :: Mathematics
Classifier: Topic :: Education
Classifier: License :: OSI Approved :: GNU Lesser General Public License v3 (LGPLv3)
License-File: license.py
License-File: COPYING
License-File: COPYING.LESSER
